{"data": {"trees": [{"nodes": {"5u56hinm7n5fdb8i": {"children": ["46ghmr5j51ri32", "3r3vdkvrq0qy2k8tq"], "id": "5u56hinm7n5fdb8i", "title": "Selector"}, "ptrfhgkpge7qwc58o": {"id": "ptrfhgkpge7qwc58o", "title": "Keeper"}, "o3jcbqg12iz4ba9": {"children": ["v4litupxpkid0dkw"], "id": "o3jcbqg12iz4ba9", "title": "Repeater"}, "vgze2gu8e6uovxjw9": {"properties": {"theirDefenceArea": "false", "outsideField": "true"}, "id": "vgze2gu8e6uovxjw9", "title": "BallInDefenseAreaAndStill"}, "ekez1lc00hspup": {"id": "ekez1lc00hspup", "title": "GetBall"}, "v4litupxpkid0dkw": {"children": ["xgu1p295kw93qk8", "acgtq84tchayy1or", "ptrfhgkpge7qwc58o"], "id": "v4litupxpkid0dkw", "title": "Selector"}, "o9f8fxmu6e0h7t": {"properties": {"RotateToTheirGoal": "true", "Angle": "0", "maxVel": "0.5", "BallPlacement": "false"}, "id": "o9f8fxmu6e0h7t", "title": "DribbleRotate"}, "bxxewub4lr2e16v": {"children": ["v97vjfarlmuf9bf5", "8w7xp90rkscayqm"], "id": "bxxewub4lr2e16v", "title": "Sequence"}, "5f53g1cyfsq6s": {"properties": {"Keeper": "true"}, "id": "5f53g1cyfsq6s", "title": "InterceptBall"}, "v97vjfarlmuf9bf5": {"id": "v97vjfarlmuf9bf5", "title": "BallKickedToOurGoal"}, "3r3vdkvrq0qy2k8tq": {"children": ["442wnhvzcos5l6fgc", "manp9ag53kcv8jwdn"], "id": "3r3vdkvrq0qy2k8tq", "title": "Sequence"}, "manp9ag53kcv8jwdn": {"children": ["rqknv8jefag2vfjc", "a2c0bwakz850sit", "o9f8fxmu6e0h7t", "gsh09zbfjy9lj1558"], "id": "manp9ag53kcv8jwdn", "title": "MemSequence"}, "nifjrq8lcs8tr7": {"id": "nifjrq8lcs8tr7", "title": "IsBallCloseToBorder"}, "rqknv8jefag2vfjc": {"properties": {"Position": "{-1.6,0}", "distanceBehindBall": "0.01", "goBehindBall": "true", "maxVel": "0.8"}, "id": "rqknv8jefag2vfjc", "title": "GoToPos"}, "acgtq84tchayy1or": {"children": ["vgze2gu8e6uovxjw9", "5u56hinm7n5fdb8i"], "id": "acgtq84tchayy1or", "title": "MemSequence"}, "wt9ez77ab6zvhqd": {"properties": {"getBallFromSide": "true", "avoidBall": "true"}, "id": "wt9ez77ab6zvhqd", "title": "BasicGoToPos"}, "4t6ogrizi9b1ls": {"properties": {}, "id": "4t6ogrizi9b1ls", "title": "Kick"}, "s2disr763itf42": {"properties": {"ourDefenseArea": "true", "useRobot": "false", "margin": "0.1", "outsideField": "true"}, "id": "s2disr763itf42", "title": "IsInDefenseArea"}, "gsh09zbfjy9lj1558": {"properties": {}, "id": "gsh09zbfjy9lj1558", "title": "Kick"}, "i7m2ztncl5niv1": {"children": ["wt9ez77ab6zvhqd", "ekez1lc00hspup", "jd2x538oxffop18x", "4rwwoj6y6jiwh", "4t6ogrizi9b1ls"], "id": "i7m2ztncl5niv1", "title": "MemSequence"}, "jd2x538oxffop18x": {"properties": {"maxTicks": "50", "distance": "0.10", "dribbleOnTerminate": "true", "forwardDirection": "false"}, "id": "jd2x538oxffop18x", "title": "Dribble"}, "46ghmr5j51ri32": {"children": ["nifjrq8lcs8tr7", "y86b4i6c53rxii4bx"], "id": "46ghmr5j51ri32", "title": "MemSequence"}, "phgpzxou1ceze6ua": {"id": "phgpzxou1ceze6ua", "title": "HasBall"}, "442wnhvzcos5l6fgc": {"properties": {"useRobot": "false", "margin": "0.1", "ourDefenseArea": "true"}, "id": "442wnhvzcos5l6fgc", "title": "IsInDefenseArea"}, "a2c0bwakz850sit": {"properties": {"maxTime": "5.0"}, "id": "a2c0bwakz850sit", "title": "GetBall"}, "y86b4i6c53rxii4bx": {"children": ["s2disr763itf42", "i7m2ztncl5niv1"], "id": "y86b4i6c53rxii4bx", "title": "Sequence"}, "xgu1p295kw93qk8": {"children": ["bxxewub4lr2e16v", "5f53g1cyfsq6s"], "id": "xgu1p295kw93qk8", "title": "MemSequence"}, "8w7xp90rkscayqm": {"children": ["phgpzxou1ceze6ua"], "id": "8w7xp90rkscayqm", "title": "Inverter"}, "4rwwoj6y6jiwh": {"properties": {"RotateToTheirGoal": "true", "maxVel": "0.5"}, "id": "4rwwoj6y6jiwh", "title": "DribbleRotate"}}, "root": "o3jcbqg12iz4ba9", "title": "DemoKeeper"}]}, "name": "DemoKeeper"}